pyensae/__init__.py
pyensae/_pylint_common.py
pyensae/cli/__init__.py
pyensae/cli/head_cli.py
pyensae/cli/tail_cli.py
pyensae/datasource/__init__.py
pyensae/datasource/convert.py
pyensae/datasource/geodata.py
pyensae/datasource/http_retrieve.py
pyensae/filehelper/__init__.py
pyensae/filehelper/content_helper.py
pyensae/filehelper/decompress_helper.py
pyensae/filehelper/format_helper.py
pyensae/filehelper/magic_file.py
pyensae/finance/__init__.py
pyensae/finance/astock.py
pyensae/graphhelper/__init__.py
pyensae/graphhelper/_colormap.py
pyensae/graphhelper/blockdiag_helper.py
pyensae/graphhelper/corrplot.py
pyensae/graphhelper/graphviz_helper.py
pyensae/graphhelper/linkage.py
pyensae/graphhelper/magic_graph.py
pyensae/graphhelper/mapplot.py
pyensae/graphhelper/matplotlib_helper.py
pyensae/languages/CSharpLexer.g4
pyensae/languages/CSharpLexer.py
pyensae/languages/CSharpLexer.tokens
pyensae/languages/CSharpLexerBase.py
pyensae/languages/CSharpParser.g4
pyensae/languages/CSharpParser.py
pyensae/languages/CSharpParser.tokens
pyensae/languages/CSharpParserBase.py
pyensae/languages/CSharpParserListener.py
pyensae/languages/CSharpPreprocessorParser.g4
pyensae/languages/CSharpPreprocessorParser.py
pyensae/languages/CSharpPreprocessorParser.tokens
pyensae/languages/CSharpPreprocessorParserListener.py
pyensae/languages/DOT.g4
pyensae/languages/DOT.tokens
pyensae/languages/DOTLexer.py
pyensae/languages/DOTLexer.tokens
pyensae/languages/DOTListener.py
pyensae/languages/DOTParser.py
pyensae/languages/Python3.g4
pyensae/languages/Python3.tokens
pyensae/languages/Python3Lexer.py
pyensae/languages/Python3Lexer.tokens
pyensae/languages/Python3Listener.py
pyensae/languages/Python3Parser.py
pyensae/languages/R.g4
pyensae/languages/R.tokens
pyensae/languages/RFilter.g4
pyensae/languages/RFilter.py
pyensae/languages/RFilter.tokens
pyensae/languages/RFilterListener.py
pyensae/languages/RLexer.py
pyensae/languages/RLexer.tokens
pyensae/languages/RListener.py
pyensae/languages/RParser.py
pyensae-1.3.967.dist-info/LICENSE.txt
pyensae-1.3.967.dist-info/METADATA
pyensae-1.3.967.dist-info/WHEEL
pyensae-1.3.967.dist-info/entry_points.txt
pyensae-1.3.967.dist-info/top_level.txt
pyensae-1.3.967.dist-info/RECORD
