Metadata-Version: 2.1
Name: pyensae
Version: 1.3.967
Summary: Helpers for teaching purposes (includes sqllite helpers).
Home-page: http://www.xavierdupre.fr/app/pyensae/helpsphinx/index.html
Author: Xavier Dupré
Author-email: xavier.dupre@gmail.com
License: MIT
Download-URL: https://github.com/sdpython/pyensae/
Keywords: pyensae,ENSAE,sqllite,database,teachings
Platform: UNKNOWN
Classifier: Programming Language :: Python :: 3
Classifier: Intended Audience :: Developers
Classifier: Topic :: Scientific/Engineering
Classifier: Topic :: Education
Classifier: License :: OSI Approved :: MIT License
Classifier: Development Status :: 5 - Production/Stable
License-File: LICENSE.txt
Requires-Dist: pyquickhelper (>=1.8)
Requires-Dist: numpy (>=1.18)
Requires-Dist: pandas (>=1.0)
Requires-Dist: matplotlib (>=3.0)
Provides-Extra: all
Requires-Dist: pyquickhelper (>=1.8) ; extra == 'all'
Requires-Dist: numpy (>=1.18) ; extra == 'all'
Requires-Dist: pandas (>=1.0) ; extra == 'all'
Requires-Dist: matplotlib (>=3.0) ; extra == 'all'
Requires-Dist: blockdiag ; extra == 'all'
Requires-Dist: cartopy ; extra == 'all'
Requires-Dist: dbread ; extra == 'all'
Requires-Dist: geopandas ; extra == 'all'
Requires-Dist: shapely ; extra == 'all'
Requires-Dist: pyshp ; extra == 'all'
Requires-Dist: pylzma ; extra == 'all'
Requires-Dist: pandas-datareader ; extra == 'all'
Requires-Dist: yahoo-historical (>=0.4) ; extra == 'all'
Requires-Dist: antlr4-python3-runtime (>=4.8) ; extra == 'all'
Requires-Dist: folium ; extra == 'all'
Requires-Dist: qgrid ; extra == 'all'
Requires-Dist: easydev ; extra == 'all'
Provides-Extra: datasource
Requires-Dist: dbread ; extra == 'datasource'
Requires-Dist: geopandas ; extra == 'datasource'
Requires-Dist: shapely ; extra == 'datasource'
Requires-Dist: pyshp ; extra == 'datasource'
Requires-Dist: pylzma ; extra == 'datasource'
Provides-Extra: finance
Requires-Dist: pandas-datareader ; extra == 'finance'
Requires-Dist: yahoo-historical (>=0.4) ; extra == 'finance'
Provides-Extra: graphhelper
Requires-Dist: matplotlib (>=3.0) ; extra == 'graphhelper'
Provides-Extra: languages
Requires-Dist: antlr4-python3-runtime (>=4.10) ; extra == 'languages'
Provides-Extra: notebookhelper
Requires-Dist: folium ; extra == 'notebookhelper'
Requires-Dist: qgrid ; extra == 'notebookhelper'
